{
    "ativo": {
        "2up3va8": {
            "user": "5522992238683@c.us",
            "limpar_msg_saida": {
                "33333333": {
                    "id_whatsapp": "3EB081AE7FD26BA17542",
                    "timestamp": 1662125919
                },
                "333333334": {
                    "id_whatsapp": "3EB03A8F84DCB40A5A78",
                    "timestamp": 1662126978
                }
            }
        },
        "5522992238683@c.us": {
            "taskId": "2up3va8",
            "ultima_msg_enviada": "333333334",
            "msgs_enviada": {
                "3EB092506630F3E1169F": "333333334",
                "3EB03A8F84DCB40A5A78": "333333334"
            }
        }
    },
    "inativo": {}
}